README.md
setup.py
Turtle/__init__.py
Turtle/globalvar.py
Turtle/init_turtle.py
Turtle/waffle_turtle.py
game/the_forth_submarine.py
micropython_Turtle.egg-info/PKG-INFO
micropython_Turtle.egg-info/SOURCES.txt
micropython_Turtle.egg-info/dependency_links.txt
micropython_Turtle.egg-info/top_level.txt