Metadata-Version: 1.0
Name: micropython-Turtle
Version: 0.0.2.1
Summary: A Turtle for micropython and add a little game
Home-page: UNKNOWN
Author: David Huang
Author-email: menghua0416@hotmail.com
License: MIT
Platform: UNKNOWN
